lzw3/__init__.py
lzw3/compressor.py
lzw3/decompressor.py
lzw3/helpers.py
lzw3/commons/__init__.py
lzw3/commons/constants.py
lzw3/commons/log.py
lzw3/commons/utils.py
lzw3/io/__init__.py
lzw3/io/bit.py
lzw3/io/byte.py
lzw3/res/__init__.py
lzw3/res/compress_help.txt
lzw3/res/uncompress_help.txt
lzw3/res/utils.py
lzw3-0.3.data/scripts/compress
lzw3-0.3.data/scripts/uncompress
lzw3-0.3.dist-info/LICENSE
lzw3-0.3.dist-info/METADATA
lzw3-0.3.dist-info/WHEEL
lzw3-0.3.dist-info/top_level.txt
lzw3-0.3.dist-info/RECORD
