Metadata-Version: 2.1
Name: lzw3
Version: 0.3
Summary: Compressor and decompressor for arbitrary files that use LZW algorithm
Home-page: https://github.com/Docheinstein/lzw3
Author: Stefano Dottore
Author-email: docheinstein@gmail.com
License: MIT
Keywords: lzw lzw3 compressor decompressor compression compress uncompress
Platform: UNKNOWN
Requires-Python: >=3.5
